version/__init__.py
version/cli.py
version/increment_command.py
version/tag_command.py
version/version.py
pyversion-0.5.7.dist-info/LICENSE
pyversion-0.5.7.dist-info/METADATA
pyversion-0.5.7.dist-info/WHEEL
pyversion-0.5.7.dist-info/entry_points.txt
pyversion-0.5.7.dist-info/pbr.json
pyversion-0.5.7.dist-info/top_level.txt
pyversion-0.5.7.dist-info/RECORD
