Metadata-Version: 2.1
Name: pyversion
Version: 0.5.7
Summary: Python package versioning made simple
Home-page: https://github.com/lingster/pyversion
Author: Kyle Rockman - ported to python3 by Ling Li
Author-email: kyle.rockman@mac.com, email@ling-li.com
License: UNKNOWN
Platform: UNKNOWN
Classifier: Environment :: Console
Classifier: Intended Audience :: Developers
Classifier: Intended Audience :: Information Technology
Classifier: License :: OSI Approved :: Apache Software License
Classifier: Operating System :: OS Independent
Classifier: Programming Language :: Python
Classifier: Programming Language :: Python :: 3 :: Only
Requires-Dist: ansimarkup (==1.4.0)
Requires-Dist: better-exceptions-fork (==0.2.1.post6)
Requires-Dist: certifi (==2018.11.29)
Requires-Dist: chardet (==3.0.4)
Requires-Dist: colorama (==0.4.1)
Requires-Dist: coverage (==5.0a4)
Requires-Dist: coveralls (==1.5.1)
Requires-Dist: docopt (==0.6.2)
Requires-Dist: idna (==2.8)
Requires-Dist: loguru (==0.2.4)
Requires-Dist: packaging (==18.0)
Requires-Dist: pbr (==5.1.1)
Requires-Dist: pygments (==2.3.1)
Requires-Dist: pyparsing (==2.3.1)
Requires-Dist: requests (==2.21.0)
Requires-Dist: six (==1.12.0)
Requires-Dist: urllib3 (==1.24.1)
